CHANGELOG.rst
MANIFEST.in
README.rst
fresco_sqlalchemy.py
setup.py
fresco_sqlalchemy.egg-info/PKG-INFO
fresco_sqlalchemy.egg-info/SOURCES.txt
fresco_sqlalchemy.egg-info/dependency_links.txt
fresco_sqlalchemy.egg-info/not-zip-safe
fresco_sqlalchemy.egg-info/requires.txt
fresco_sqlalchemy.egg-info/top_level.txt