Metadata-Version: 1.1
Name: fresco-sqlalchemy
Version: 0.1
Summary: Fresco/SQLAlchemy integration
Home-page: https://bitbucket.org/ollyc/fresco-sqlalchemy
Author: Oliver Cope
Author-email: oliver@redgecko.org
License: BSD
Platform: UNKNOWN
Classifier: License :: OSI Approved :: BSD License
Classifier: Topic :: Internet :: WWW/HTTP :: WSGI :: Middleware
Classifier: Programming Language :: Python :: 2.6
Classifier: Programming Language :: Python :: 2.7
Classifier: Programming Language :: Python :: 3.3
